rfrefactoring/__init__.py
rfrefactoring/refactorHelper.py
rfrefactoring/refactoringFacade.py
rfrefactoring/reference.py
rfrefactoring/referencesFinder.py
rfrefactoring/referencesMethods.py
rfrefactoring/testDataDependencyBuilder.py
rfrefactoring/testDataVisitor.py
rfrefactoring/newRfrefactoring/__init__.py
rfrefactoring/newRfrefactoring/newRefactoringFacade.py
rfrefactoring/newRfrefactoring/rfRefactorHelper.py
rfrefactoring/newRfrefactoring/builder/__init__.py
rfrefactoring/newRfrefactoring/builder/testModelBuilder.py
rfrefactoring/newRfrefactoring/checker/__init__.py
rfrefactoring/newRfrefactoring/checker/fileChecker.py
rfrefactoring/newRfrefactoring/common/__init__.py
rfrefactoring/newRfrefactoring/common/threadWithReturn.py
rfrefactoring/newRfrefactoring/common/utility.py
rfrefactoring/newRfrefactoring/helper/__init__.py
rfrefactoring/newRfrefactoring/helper/lineKeywordsHelper.py
rfrefactoring/newRfrefactoring/keywords/__init__.py
rfrefactoring/newRfrefactoring/keywords/keywordCreator.py
rfrefactoring/newRfrefactoring/keywords/keywordFinder.py
rfrefactoring/newRfrefactoring/keywords/keywordMoveHelper.py
rfrefactoring/newRfrefactoring/keywords/keywordPrinter.py
rfrefactoring/newRfrefactoring/keywords/keywordRenamer.py
JoeLiu_RF_Refactoring-1.0.9.dist-info/LICENSE.txt
JoeLiu_RF_Refactoring-1.0.9.dist-info/METADATA
JoeLiu_RF_Refactoring-1.0.9.dist-info/WHEEL
JoeLiu_RF_Refactoring-1.0.9.dist-info/top_level.txt
JoeLiu_RF_Refactoring-1.0.9.dist-info/RECORD
