Metadata-Version: 2.1
Name: JoeLiu-RF-Refactoring
Version: 1.0.9
Summary: RF Refactoring package
Home-page: https://github.com/JoeLiu1321/RF-Refactoring
Author: Joe Liu&GeneWu
Author-email: qq555520qq@gmail.com
License: UNKNOWN
Platform: UNKNOWN
Classifier: Programming Language :: Python :: 3
Classifier: License :: OSI Approved :: MIT License
Classifier: Operating System :: OS Independent
License-File: LICENSE.txt
Requires-Dist: robotframework
